[
    {
        "title": "Tu Primera extension VSCode",
        "url": "https://www.youtube.com/watch?v=ml_nUKfjk5o&pp=ygUpaGFjZXIgdW5hIGV4dGVuc2lvbiBlbiB2aXN1YWwgc3R1ZGlvIGNvZGU%3D",
        "date": "2025-12-10 20:29",
        "file_path": "C:\\Users\\user\\Videos\\ConvertMp4\\Tu Primera extension VSCode.mp4"
    },
    {
        "title": "[ 4K 120FPS ] Michael Jackson - Billie Jean | Live In Munich, 1997 (BluRay, WideScreen, Remastered)",
        "url": "https://www.youtube.com/watch?v=lVpO6QW2p24",
        "date": "2025-11-29 12:15",
        "file_path": "C:\\Users\\user\\Videos\\ConvertMp4\\[ 4K 120FPS ] Michael Jackson - Billie Jean ｜ Live In Munich, 1997 (BluRay, WideScreen, Remastered).mp4"
    },
    {
        "title": "[ 4K 120FPS ] Michael Jackson - Billie Jean | Live In Munich, 1997 (BluRay, WideScreen, Remastered)",
        "url": "https://www.youtube.com/watch?v=lVpO6QW2p24",
        "date": "2025-11-29 12:14",
        "file_path": "C:\\Users\\user\\Documents\\Convertidor YT a Mp4\\[ 4K 120FPS ] Michael Jackson - Billie Jean ｜ Live In Munich, 1997 (BluRay, WideScreen, Remastered).mp4"
    },
    {
        "title": "Michael Jackson | Thriller - Live in Bucharest October 1st, 1992 (4K60FPS)",
        "url": "https://www.youtube.com/watch?v=Q1BGrVynDeM",
        "date": "2025-11-29 12:12",
        "file_path": "C:\\Users\\user\\Documents\\Convertidor YT a Mp4\\Michael Jackson ｜ Thriller - Live in Bucharest October 1st, 1992 (4K60FPS).mp4"
    },
    {
        "title": "Michael Jackson | Thriller - Live in Bucharest October 1st, 1992 (4K60FPS)",
        "url": "https://www.youtube.com/watch?v=Q1BGrVynDeM",
        "date": "2025-11-29 12:10",
        "file_path": "C:\\Users\\user\\Documents\\Convertidor YT a Mp4\\Michael Jackson ｜ Thriller - Live in Bucharest October 1st, 1992 (4K60FPS).mp4"
    },
    {
        "title": "Tutorial N° 03: Creación de Títulos, Partidas y Costos Unitarios - S10 Costos y Presupuestos",
        "url": "https://www.youtube.com/watch?v=PBmKbqIvxJE",
        "date": "2025-11-28 16:48"
    }
]